oslash/__init__.py
oslash/cont.py
oslash/do.py
oslash/either.py
oslash/identity.py
oslash/ioaction.py
oslash/list.py
oslash/maybe.py
oslash/monadic.py
oslash/observable.py
oslash/reader.py
oslash/state.py
oslash/writer.py
oslash/typing/__init__.py
oslash/typing/applicative.py
oslash/typing/functor.py
oslash/typing/monad.py
oslash/typing/monoid.py
oslash/util/__init__.py
oslash/util/basic.py
oslash/util/fn.py
oslash/util/numerals.py
oslash-2.0.0.dist-info/METADATA
oslash-2.0.0.dist-info/WHEEL
oslash-2.0.0.dist-info/licenses/LICENSE
oslash-2.0.0.dist-info/RECORD
