Metadata-Version: 2.4
Name: oslash
Version: 2.0.0
Summary: Functional library for Functors, Applicatives, and Monads in Python 3.12+
Project-URL: Homepage, https://github.com/dbrattli/oslash
Project-URL: Repository, https://github.com/dbrattli/oslash
Project-URL: Bug Tracker, https://github.com/dbrattli/oslash/issues
Author-email: Dag Brattli <dag@brattli.net>
Maintainer-email: Dag Brattli <dag@brattli.net>
License: Copyright 2020 Dag Brattli
License-File: LICENSE
Classifier: Development Status :: 5 - Production/Stable
Classifier: Environment :: Other Environment
Classifier: Intended Audience :: Developers
Classifier: License :: OSI Approved :: MIT License
Classifier: Operating System :: OS Independent
Classifier: Programming Language :: Python :: 3.12
Classifier: Programming Language :: Python :: 3.13
Classifier: Programming Language :: Python :: 3.14
Classifier: Topic :: Software Development :: Libraries :: Python Modules
Classifier: Typing :: Typed
Requires-Python: >=3.12
Provides-Extra: dev
Requires-Dist: pre-commit>=3.0; extra == 'dev'
Requires-Dist: pyright>=1.1.407; extra == 'dev'
Requires-Dist: pytest-cov>=4.0; extra == 'dev'
Requires-Dist: pytest>=8.0; extra == 'dev'
Requires-Dist: ruff>=0.14.5; extra == 'dev'
